LICENSE
README.md
arxiv2kindle.py
arxiv2kindle-0.1.3.dist-info/entry_points.txt
arxiv2kindle-0.1.3.dist-info/LICENSE
arxiv2kindle-0.1.3.dist-info/WHEEL
arxiv2kindle-0.1.3.dist-info/METADATA
arxiv2kindle-0.1.3.dist-info/RECORD
