Metadata-Version: 2.1
Name: arxiv2kindle
Version: 0.1.3
Summary: A simple tool to recompile arxiv papers to kindle-like format.
Home-page: https://github.com/dmitriy-serdyuk/arxiv2kindle
License: MIT
Keywords: arxiv,latex,kindle
Author: Dmitriy Serdyuk
Author-email: dmitriy@serdyuk.cc
Requires-Python: >=3.7,<4.0
Classifier: Environment :: Console
Classifier: License :: OSI Approved :: MIT License
Classifier: Operating System :: OS Independent
Classifier: Programming Language :: Python :: 3
Classifier: Programming Language :: Python :: 3.7
Classifier: Programming Language :: Python :: 3.8
Requires-Dist: arxiv (>=0.5.3,<0.6.0)
Requires-Dist: requests
Project-URL: Repository, https://github.com/dmitriy-serdyuk/arxiv2kindle
